sphinx_notion/__init__.py
sphinx_notion/__main__.py
sphinx_notion/builders.py
sphinx_notion/types.py
sphinx_notion/writers.py
sphinx_notion/nodes/__init__.py
sphinx_notion/nodes/literal_block.py
sphinx_notion-0.0.7.dist-info/licenses/LICENSE
sphinx_notion-0.0.7.dist-info/METADATA
sphinx_notion-0.0.7.dist-info/WHEEL
sphinx_notion-0.0.7.dist-info/top_level.txt
sphinx_notion-0.0.7.dist-info/RECORD
