Metadata-Version: 2.4
Name: sphinx-notion
Version: 0.0.7
Summary: Sphinx extension to generate JSON for Notion API from Sphinx documentation
Author-email: nikkie <takuyafjp+develop@gmail.com>
License: MIT License
Project-URL: Repository, https://github.com/ftnext/sphinx-notion
Keywords: Sphinx,Notion
Classifier: Development Status :: 1 - Planning
Classifier: License :: OSI Approved :: MIT License
Classifier: Intended Audience :: Developers
Classifier: Framework :: Sphinx
Classifier: Framework :: Sphinx :: Extension
Classifier: Topic :: Documentation
Classifier: Topic :: Documentation :: Sphinx
Classifier: Topic :: Software Development :: Documentation
Classifier: Programming Language :: Python
Classifier: Programming Language :: Python :: 3
Classifier: Programming Language :: Python :: 3 :: Only
Classifier: Programming Language :: Python :: 3.10
Classifier: Programming Language :: Python :: 3.11
Classifier: Programming Language :: Python :: 3.12
Classifier: Programming Language :: Python :: 3.13
Classifier: Programming Language :: Python :: 3.14
Requires-Python: >=3.10
License-File: LICENSE
Requires-Dist: Sphinx
Provides-Extra: dev
Requires-Dist: taskipy; extra == "dev"
Requires-Dist: autoflake; extra == "dev"
Requires-Dist: pyupgrade; extra == "dev"
Requires-Dist: black; extra == "dev"
Requires-Dist: isort; extra == "dev"
Requires-Dist: pytest; extra == "dev"
Requires-Dist: pytest-randomly; extra == "dev"
Requires-Dist: flake8; extra == "dev"
Requires-Dist: mypy; extra == "dev"
Requires-Dist: types-docutils; extra == "dev"
Requires-Dist: types-Pygments; extra == "dev"
Dynamic: license-file
